wtwco_igloo/__init__.py
wtwco_igloo/api_client/__init__.py
wtwco_igloo/api_client/api/__init__.py
wtwco_igloo/api_client/api/calculation_pools/__init__.py
wtwco_igloo/api_client/api/data_groups/__init__.py
wtwco_igloo/api_client/api/data_table/__init__.py
wtwco_igloo/api_client/api/data_tables/__init__.py
wtwco_igloo/api_client/api/input_data/__init__.py
wtwco_igloo/api_client/api/job_status/__init__.py
wtwco_igloo/api_client/api/jobs/__init__.py
wtwco_igloo/api_client/api/models/__init__.py
wtwco_igloo/api_client/api/o_data/__init__.py
wtwco_igloo/api_client/api/output_data/__init__.py
wtwco_igloo/api_client/api/projects/__init__.py
wtwco_igloo/api_client/api/result_table/__init__.py
wtwco_igloo/api_client/api/result_tables/__init__.py
wtwco_igloo/api_client/api/run_results/__init__.py
wtwco_igloo/api_client/api/runs/__init__.py
wtwco_igloo/api_client/api/uploaded_files/__init__.py
wtwco_igloo/api_client/api/workspaces/__init__.py
wtwco_igloo/api_client/models/__init__.py
wtwco_igloo/api_client/types/__init__.py
wtwco_igloo/extensions/__init__.py
wtwco_igloo/extensions/calculation_pool.py
wtwco_igloo/extensions/config.py
wtwco_igloo/extensions/connection.py
wtwco_igloo/extensions/job.py
wtwco_igloo/extensions/model.py
wtwco_igloo/extensions/project.py
wtwco_igloo/extensions/run.py
wtwco_igloo/extensions/run_result.py
wtwco_igloo/extensions/run_result_table_node.py
wtwco_igloo/extensions/table_definition.py
wtwco_igloo/extensions/uploaded_file.py
wtwco_igloo/extensions/utils/authentication/authenticated_client_with_retries.py
wtwco_igloo/extensions/utils/authentication/authentication_base.py
wtwco_igloo/extensions/utils/authentication/authentication_with_refresh.py
wtwco_igloo/extensions/utils/authentication/authentication_without_refresh.py
wtwco_igloo/extensions/utils/authentication/custom_http_client.py
wtwco_igloo/extensions/utils/authentication/retry_httpx_client.py
wtwco_igloo/extensions/utils/authentication/token_cache.py
wtwco_igloo-2.1.0.dist-info/entry_points.txt
wtwco_igloo-2.1.0.dist-info/licenses/LICENSE.txt
wtwco_igloo-2.1.0.dist-info/METADATA
wtwco_igloo-2.1.0.dist-info/WHEEL
wtwco_igloo-2.1.0.dist-info/RECORD
