Metadata-Version: 2.4
Name: wtwco-igloo
Version: 2.1.0
Summary: Python SDK for Igloo Cloud
License: MIT
License-File: LICENSE.txt
Author: WTW
Author-email: software.support@wtwco.com
Requires-Python: >=3.10,<3.14
Classifier: License :: OSI Approved :: MIT License
Classifier: Programming Language :: Python :: 3
Classifier: Programming Language :: Python :: 3.10
Classifier: Programming Language :: Python :: 3.11
Classifier: Programming Language :: Python :: 3.12
Classifier: Programming Language :: Python :: 3.13
Requires-Dist: aiofiles (>=24.1.0,<25.0.0)
Requires-Dist: aiohttp (>=3.13.3,<4.0.0)
Requires-Dist: azure-core (>=1.38.0,<2.0.0)
Requires-Dist: azure-storage-blob (>=12.20.0,<13.0.0)
Requires-Dist: cryptography (>=44.0.1,<45.0.0)
Requires-Dist: msal[broker] (>=1.33.0,<2.0.0)
Requires-Dist: pydantic (>=2.9.2,<3.0.0)
Requires-Dist: urllib3 (>=2.6.3,<3.0.0)
Requires-Dist: wtwco-igloo-cloud-api-client (==5.0.0)
